.requirements.txt
LICENSE
MANIFEST.in
README.md
launcher
setup.py
sciexp2/__init__.py
sciexp2/common/__init__.py
sciexp2/common/filter.py
sciexp2/common/instance.py
sciexp2/common/pp.py
sciexp2/common/progress.py
sciexp2/common/text.py
sciexp2/common/utils.py
sciexp2/expdef/__init__.py
sciexp2/expdef/env.py
sciexp2/expdef/experiments.py
sciexp2/expdef/launcher.py
sciexp2/expdef/templates.py
sciexp2/expdef/system/__init__.py
sciexp2/expdef/system/gridengine.py
sciexp2/expdef/system/shell.py
sciexp2/expdef/templates/dacupc-gridengine.dsc
sciexp2/expdef/templates/gridengine.dsc
sciexp2/expdef/templates/gridengine.tpl
sciexp2/expdef/templates/shell.dsc
sciexp2/expdef/templates/shell.tpl
sciexp2_expdef.egg-info/PKG-INFO
sciexp2_expdef.egg-info/SOURCES.txt
sciexp2_expdef.egg-info/dependency_links.txt
sciexp2_expdef.egg-info/requires.txt
sciexp2_expdef.egg-info/top_level.txt