Metadata-Version: 2.4
Name: sciexp2-expdef
Version: 2.2.0
Summary: Experiment definition framework for SciExp²
Home-page: https://sciexp2-expdef.readthedocs.io/
Author: Lluís Vilanova
Author-email: llvilanovag@gmail.com
License: GNU General Public License (GPL) version 3 or later
Platform: any
Classifier: Development Status :: 5 - Production/Stable
Classifier: Environment :: Console
Classifier: Intended Audience :: Science/Research
Classifier: License :: OSI Approved :: GNU General Public License (GPL)
Classifier: Programming Language :: Python
Classifier: Topic :: Scientific/Engineering
License-File: LICENSE
Requires-Dist: ipython
Requires-Dist: jinja2
Requires-Dist: numpy
Requires-Dist: pystache
Requires-Dist: six
Requires-Dist: tqdm
Dynamic: author
Dynamic: author-email
Dynamic: classifier
Dynamic: description
Dynamic: home-page
Dynamic: license
Dynamic: license-file
Dynamic: platform
Dynamic: requires-dist
Dynamic: summary
